{
  "id": "2026-07-01-confusa-e-felice-carmen-consoli",
  "date": "2026-07-01",
  "day_name": "mercoledì",
  "status": "published",
  "song_title": "Confusa E Felice",
  "artist": "Carmen Consoli",
  "dedication_title": "La dedica del giorno",
  "dedication_text": "Beh, quest'oggi, la mia dedica. Il testo della canzone basta che ascolti quello e troverai tutte le risposte♥️",
  "audio": {
    "url": "https://open.spotify.com/track/0sgF2OErypqDCb0lIoZycS?si=Iu3_u3-QTjSw7bcQ3W6BkA",
    "type": "spotify"
  },
  "vote": {
    "url": "https://docs.google.com/forms/d/17VuesL0BOupyw5M5MNCLs1gq_uqZioVKVkGC8oFfn38/viewform"
  },
  "image": {
    "path": "/images/dedications/2026-07-01-confusa-e-felice-carmen-consoli.webp",
    "alt": "Dedica musicale Confusa E Felice di Carmen Consoli",
    "mode": "raw",
    "source": "public/images/upload/2026-07-01-confusa-e-felice-carmen-consoli.webp"
  },
  "short_phrase": "Confusa e felice",
  "tags": [
    "musica",
    "emozioni",
    "dedica"
  ],
  "seo": {
    "title": "Confusa E Felice - Carmen Consoli | DDGPilliSite",
    "description": "Dedica musicale del giorno con \"Confusa E Felice\" di Carmen Consoli."
  },
  "created_at": "2026-07-01T15:42:52.196181+02:00",
  "updated_at": "2026-07-01T15:42:52.793942+02:00",
  "voteAverage": null,
  "thoughtsText": "",
  "reactions": {
    "down": 0,
    "like": 0,
    "heart": 0,
    "sun": 0
  },
  "votes": [],
  "thoughts": [],
  "reactionEntries": [],
  "date_it": "1 luglio 2026"
}